{"headline": {"main": "Think America Nearer War", "kicker": "1"}, "lead_paragraph": "LONDON, Saturday, Nov. 1 -- Some London newspapers today stressed the United States, nearness to open war as result of the sinking of the Reuben James, which, according to British sources, probably was the victim of one of the \"wolf packs\" of German submarines preying on Atlantic convoys.", "news_desk": null, "document_type": "article", "blog": [], "abstract": null, "print_page": "3", "type_of_material": "Article", "source": "The New York Times", "_id": "4fc231cd45c1498b0d6685e2", "keywords": [], "pub_date": "1941-11-01T00:00:00Z", "subsection_name": null, "multimedia": [], "snippet": "LONDON, Saturday, Nov. 1 -- Some London newspapers today stressed the United States, nearness to open war as result of the sinking of the Reuben James, which, according to British sources, probably was the victim of one of the \"wolf packs\" of Germ...", "slideshow_credits": null, "word_count": 367, "byline": {"original": "By The United Press", "organization": "The United Press", "person": []}, "web_url": "http://query.nytimes.com/gst/abstract.html?res=9506E3DC143AEF3ABC4953DFB767838A659EDE", "section_name": null}