{"headline": {"main": "Eleven British Planes Claimed"}, "lead_paragraph": null, "news_desk": null, "document_type": "article", "blog": [], "abstract": "Itals rept RAF raids on Derna and Tripoli, Libya", "print_page": "3", "type_of_material": "Article", "source": "The New York Times", "_id": "4fc2085045c1498b0d5b046c", "keywords": [{"name": "glocations", "value": "MEDITERRANEAN, AFRICAN, BALKAN AND NEAR EAST AREAS"}, {"name": "subject", "value": "EUROPEAN WAR"}, {"name": "subject", "value": "MILITARY ACTION"}], "pub_date": "1941-10-15T00:00:00Z", "subsection_name": null, "multimedia": [], "snippet": "Itals rept RAF raids on Derna and Tripoli, Libya...", "slideshow_credits": null, "word_count": 117, "byline": null, "web_url": "http://query.nytimes.com/gst/abstract.html?res=940DE6DC1E3FE13BBC4D52DFB667838A659EDE", "section_name": null}