{"headline": {"main": "BROADCASTERS DENY PREJUDICE CHARGES; CBS and NBC Answer Flynn on Charges of Unfairness"}, "lead_paragraph": "Replying by John T. Flynn, chairman of the New York chapter of the American First Committee, who accused CBS and the other major radio networks of prejudice in favor of the interventionist cause at a rally in Madison Square Garden last night, the Columbia Broadcasting System issued the following statement:", "news_desk": null, "document_type": "article", "blog": [], "abstract": "CBS and NBC reply to Flynn", "print_page": "3", "type_of_material": "Article", "source": "The New York Times", "_id": "4fc211ef45c1498b0d5daeb0", "keywords": [{"name": "glocations", "value": "UNITED STATES, STATUS OF"}, {"name": "subject", "value": "EUROPEAN WAR"}], "pub_date": "1941-10-31T00:00:00Z", "subsection_name": null, "multimedia": [], "snippet": "Replying by John T. Flynn, chairman of the New York chapter of the American First Committee, who accused CBS and the other major radio networks of prejudice in favor of the interventionist cause at a rally in Madison Square Garden last night, the ...", "slideshow_credits": null, "word_count": 312, "byline": null, "web_url": "http://query.nytimes.com/gst/abstract.html?res=9A00E5D81E3FE13BBC4950DFB667838A659EDE", "section_name": null}