{"headline": {"main": "Heavy Troop Moves Reported"}, "lead_paragraph": null, "news_desk": null, "document_type": "article", "blog": [], "abstract": "Brasov repts German troop movements disrupt Rumanian train service", "print_page": "2", "type_of_material": "Article", "source": "The New York Times", "_id": "4fc20c8545c1498b0d5c22e5", "keywords": [{"name": "glocations", "value": "MEDITERRANEAN, AFRICAN, BALKAN AND NEAR EAST AREAS"}, {"name": "subject", "value": "EUROPEAN WAR"}], "pub_date": "1941-01-02T00:00:00Z", "subsection_name": null, "multimedia": [], "snippet": "Brasov repts German troop movements disrupt Rumanian train service...", "slideshow_credits": null, "word_count": 84, "byline": null, "web_url": "http://query.nytimes.com/gst/abstract.html?res=9404EFDB123DE33BBC4A53DFB766838A659EDE", "section_name": null}