{"headline": {"main": "PEACE OFFENSIVE' URGED; Dr. John A. O'Brien Asks Anti- War Convention in Capital"}, "lead_paragraph": null, "news_desk": null, "document_type": "article", "blog": [], "abstract": "Urges mass anti-war demonstrations", "print_page": "5", "type_of_material": "Article", "source": "The New York Times", "_id": "4fc214bf45c1498b0d5e7653", "keywords": [{"name": "persons", "value": "O'BRIEN , JOHN A"}, {"name": "glocations", "value": "UNITED STATES, STATUS OF"}, {"name": "subject", "value": "EUROPEAN WAR"}], "pub_date": "1941-11-03T00:00:00Z", "subsection_name": null, "multimedia": [], "snippet": "Urges mass anti-war demonstrations...", "slideshow_credits": null, "word_count": 159, "byline": null, "web_url": "http://query.nytimes.com/gst/abstract.html?res=9C07E7DB143AEF3ABC4B53DFB767838A659EDE", "section_name": null}