{"headline": {"main": "8 SENATORS ATTACK LEASE-LEND BILL; Gen. Wood Issues Statements by Members of Three Parties"}, "lead_paragraph": "CHICAGO, Feb. 1 (UP) -- General Robert E. Wood, chairman of the American First Committee, said tonight he had been authorized by eight members of the United States Senate to issue statements of their opposition of the Administration's lease-lend bill.", "news_desk": null, "document_type": "article", "blog": [], "abstract": "Opposes lend-lease bill, statement", "print_page": "28", "type_of_material": "Article", "source": "The New York Times", "_id": "4fc2190845c1498b0d5fa203", "keywords": [{"name": "persons", "value": "BROOKS , C WAYLAND"}, {"name": "persons", "value": "CASTLE, WILLIAM R"}, {"name": "persons", "value": "CAPPER , ARTHUR"}, {"name": "persons", "value": "LA FOLLETTE , ROBERT MARION JR"}, {"name": "glocations", "value": "UNITED STATES, STATUS OF"}, {"name": "glocations", "value": "UNITED STATES, STATUS OF"}, {"name": "glocations", "value": "UNITED STATES, STATUS OF"}, {"name": "organizations", "value": "CHICAGO, UNIV OF"}, {"name": "subject", "value": "EUROPEAN WAR"}, {"name": "subject", "value": "EUROPEAN WAR"}, {"name": "subject", "value": "EUROPEAN WAR"}], "pub_date": "1941-02-02T00:00:00Z", "subsection_name": null, "multimedia": [], "snippet": "CHICAGO, Feb. 1 (UP) -- General Robert E. Wood, chairman of the American First Committee, said tonight he had been authorized by eight members of the United States Senate to issue statements of their opposition of the Administration's lease-lend b...", "slideshow_credits": null, "word_count": 253, "byline": null, "web_url": "http://query.nytimes.com/gst/abstract.html?res=9D05E6DA163BE33BBC4A53DFB466838A659EDE", "section_name": null}