{"headline": {"main": "Petain Tours Work Centers"}, "lead_paragraph": null, "news_desk": null, "document_type": "article", "blog": [], "abstract": "Petain arrives, St Etienne, to tour working class centers", "print_page": "34", "type_of_material": "Article", "source": "The New York Times", "_id": "4fc2171645c1498b0d5f1a74", "keywords": [{"name": "glocations", "value": "FRANCE"}, {"name": "subject", "value": "EUROPEAN WAR"}], "pub_date": "1941-03-02T00:00:00Z", "subsection_name": null, "multimedia": [], "snippet": "Petain arrives, St Etienne, to tour working class centers...", "slideshow_credits": null, "word_count": 56, "byline": null, "web_url": "http://query.nytimes.com/gst/abstract.html?res=9C00E7DA133DE33BBC4A53DFB566838A659EDE", "section_name": null}