{"headline": {"main": "May Change Lend-Lease Set-Up"}, "lead_paragraph": null, "news_desk": null, "document_type": "article", "blog": [], "abstract": "Roosevelt and King sign pact to speed output and aid to USSR and other anti-Axis forces; joint Canadian-U S defense output com apptmt may change Canada-U S-Brit lend-lease set-up", "print_page": "5", "type_of_material": "Article", "source": "The New York Times", "_id": "4fc21f6c45c1498b0d6164be", "keywords": [{"name": "glocations", "value": "UNITED STATES, STATUS OF"}, {"name": "subject", "value": "EUROPEAN WAR"}], "pub_date": "1941-11-06T00:00:00Z", "subsection_name": null, "multimedia": [], "snippet": "Roosevelt and King sign pact to speed output and aid to USSR and other anti-Axis forces; joint Canadian-U S defense output com apptmt may change Canada-U S-Brit lend-lease set-up...", "slideshow_credits": null, "word_count": 90, "byline": {"original": "By The United Press", "organization": "The United Press", "person": []}, "web_url": "http://query.nytimes.com/gst/abstract.html?res=9E05E2DB143AEF3ABC4E53DFB767838A659EDE", "section_name": null}