{"headline": {"main": "War Takes Hurricane Timber", "kicker": "1"}, "lead_paragraph": null, "news_desk": null, "document_type": "article", "blog": [], "abstract": null, "print_page": "S8", "type_of_material": "Article", "source": "The New York Times", "_id": "4fc22c9d45c1498b0d650bcb", "keywords": [], "pub_date": "1943-08-01T00:00:00Z", "subsection_name": null, "multimedia": [], "snippet": null, "slideshow_credits": null, "word_count": 60, "byline": null, "web_url": "http://query.nytimes.com/gst/abstract.html?res=9B07EFDC1738E33BBC4953DFBE668388659EDE", "section_name": null}