{"headline": {"main": "GOSSIP VERSUS NEWS"}, "lead_paragraph": "A Washington dispatch described the \"bits and pieces\" system by which Axis agents sometimes get news that is helpful to them. The source is gossip that seems harmless: A factory worker telling of orders for assault boats; a produce merchant telling of a Navy order for vegetables; a girl telling another girl that her boy friend, a parachute trooper, is \"going across Tuesday.\"", "news_desk": null, "document_type": "article", "blog": [], "abstract": "Ed on dangerous gossip and rumor-mongering", "print_page": "22", "type_of_material": "Editorial", "source": "The New York Times", "_id": "4fc23a7a45c1498b0d69092f", "keywords": [{"name": "subject", "value": "WAR NEWS, INFORMATION AND PROPAGANDA"}], "pub_date": "1943-01-01T00:00:00Z", "subsection_name": null, "multimedia": [], "snippet": "A Washington dispatch described the \"bits and pieces\" system by which Axis agents sometimes get news that is helpful to them. The source is gossip that seems harmless: A factory worker telling of orders for assault boats; a produce merchant tellin...", "slideshow_credits": null, "word_count": 295, "byline": null, "web_url": "http://query.nytimes.com/gst/abstract.html?res=9B0DE4DD1F31E53BBC4953DFB7668388659EDE", "section_name": null}