{"headline": {"main": "German; Day's War Communiques", "kicker": "2"}, "lead_paragraph": "A High Command communique broadcast from Berlin and recorded here by The Associated Press:", "news_desk": null, "document_type": "article", "blog": [], "abstract": null, "print_page": "2", "type_of_material": "Article", "source": "The New York Times", "_id": "4fc23a7045c1498b0d68fcfb", "keywords": [], "pub_date": "1943-01-03T00:00:00Z", "subsection_name": null, "multimedia": [], "snippet": "A High Command communique broadcast from Berlin and recorded here by The Associated Press:...", "slideshow_credits": null, "word_count": 545, "byline": null, "web_url": "http://query.nytimes.com/gst/abstract.html?res=9502E1D81E3DE533A25750C0A9679C946293D6CF", "section_name": null}