{"headline": {"main": "CHINESE HALT PUSH IN HUNAN RICE AREA; Japanese Two-Pronged Drive Is Believed Another Effort to Seize Farming Belt"}, "lead_paragraph": "CHUNGKING, China, Nov. 1 (AP) -- Japanese forces attempting a new two-pronged drive from above Tungting Lake, apparently in another effort to conquer China's Hunan Province \"rice bowl,\" have been checked or thrown back although fierce fighting is still raging, the Chinese High Command announced tonight.", "news_desk": null, "document_type": "article", "blog": [], "abstract": "US soldiers burial, New Guinea, illus", "print_page": "6", "type_of_material": "Article", "source": "The New York Times", "_id": "4fc235d545c1498b0d67b58f", "keywords": [{"name": "organizations", "value": "FAR EASTERN FRONT"}, {"name": "organizations", "value": "FAR EASTERN FRONT"}, {"name": "subject", "value": "WORLD WAR II"}, {"name": "subject", "value": "WORLD WAR II"}], "pub_date": "1943-11-02T00:00:00Z", "subsection_name": null, "multimedia": [], "snippet": "CHUNGKING, China, Nov. 1 (AP) -- Japanese forces attempting a new two-pronged drive from above Tungting Lake, apparently in another effort to conquer China's Hunan Province \"rice bowl,\" have been checked or thrown back although fierce fighting is ...", "slideshow_credits": null, "word_count": 230, "byline": null, "web_url": "http://query.nytimes.com/gst/abstract.html?res=9806E3D9113CEE3BBC4A53DFB7678388659EDE", "section_name": null}