{"headline": {"main": "NEWS SUMMARY"}, "lead_paragraph": "INTERNATIONAL A3-9 Arafat Goes to Washington; Bomb in Israel Injures 30 Yasir Arafat left Gaza for a hastily arranged meeting with President Clinton to discuss the Palestinian leader's reservations about an American blueprint for a final peace deal. Word of his departure came several hours after a car bomb rocked the commercial heart of the Israeli coastal city of Netanya, wounding more than 30 people. A1 Hundreds of uniformed young men, some waving rifles, commemorated the 36th anniversary of the founding of Mr. Arafat's Fatah movement with slogans and bursts of automatic gunfire as they moved through Ramallah, in the West Bank. A6", "news_desk": "Metropolitan Desk", "document_type": "article", "blog": [], "abstract": null, "print_page": "2", "type_of_material": "Summary", "source": "The New York Times", "_id": "4fd210618eb7c8105d784835", "keywords": [], "pub_date": "2001-01-02T00:00:00Z", "subsection_name": null, "multimedia": [], "snippet": "INTERNATIONAL   A3-9    Arafat Goes to Washington; Bomb in Israel Injures 30  Yasir Arafat left Gaza for a hastily arranged meeting with President Clinton to discuss the Palestinian leader's reservations about an American blueprint for a final pea...", "slideshow_credits": null, "word_count": 1397, "byline": null, "web_url": "http://www.nytimes.com/2001/01/02/nyregion/news-summary-248720.html", "section_name": "New York and Region"}