{"headline": {"main": "Infiltration by Enemy"}, "lead_paragraph": "AT UNITED NATIONS HEADQUARTERS, Australia, Saturday, Aug. 1 (AP) -- Allied action against enemy bases at Guadalcanal, in the Solomon Islands, disclosed that Japanese infiltrations into the island had been going on for about six weeks, a military spokesman said here today.", "news_desk": null, "document_type": "article", "blog": [], "abstract": "claim damage inflicted in Townsville raid", "print_page": "2", "type_of_material": "Article", "source": "The New York Times", "_id": "4fc21a3145c1498b0d5ff42e", "keywords": [{"name": "organizations", "value": "FAR EASTERN FRONT"}, {"name": "organizations", "value": "FAR EASTERN FRONT"}, {"name": "subject", "value": "WORLD WAR II"}, {"name": "subject", "value": "WORLD WAR II"}], "pub_date": "1942-08-01T00:00:00Z", "subsection_name": null, "multimedia": [], "snippet": "AT UNITED NATIONS HEADQUARTERS, Australia, Saturday, Aug. 1 (AP) -- Allied action against enemy bases at Guadalcanal, in the Solomon Islands, disclosed that Japanese infiltrations into the island had been going on for about six weeks, a military s...", "slideshow_credits": null, "word_count": 235, "byline": null, "web_url": "http://query.nytimes.com/gst/abstract.html?res=9405EEDF113CE33BBC4953DFBE668389659EDE", "section_name": null}