{"slideshow_credits": null, "_id": "4fc2144845c1498b0d5e54f4", "byline": null, "abstract": "Gives ambulance fund to French Red Cross", "news_desk": null, "blog": [], "section_name": null, "snippet": "Gives ambulance fund to French Red Cross...", "pub_date": "1940-02-02T00:00:00Z", "print_page": "2", "keywords": [{"name": "persons", "value": "HARJES, JOHN F"}, {"name": "organizations", "value": "NEW YORK STATE CHAMBER OF COMMERCE"}, {"name": "subject", "value": "EUROPEAN WAR"}, {"name": "subject", "value": "WELFARE WORK"}], "word_count": 120, "headline": {"main": "GETS FUND FOR AMBULANCE; French Relief Group Receives Aid From Business Men"}, "lead_paragraph": null, "subsection_name": null, "type_of_material": "Article", "document_type": "article", "source": "The New York Times", "multimedia": [], "web_url": "http://query.nytimes.com/gst/abstract.html?res=9D04E5DD1031E43ABC4A53DFB466838B659EDE"}