{"slideshow_credits": null, "_id": "4fc2096a45c1498b0d5b436c", "byline": null, "abstract": "eds", "news_desk": null, "blog": [], "section_name": null, "snippet": "eds...", "pub_date": "1940-04-01T00:00:00Z", "print_page": "36", "keywords": [{"name": "subject", "value": "PROFESSIONS"}, {"name": "subject", "value": "EUROPEAN WAR"}, {"name": "subject", "value": "DIPLOMATIC ACTION"}], "word_count": 1373, "headline": {"main": "TODAY ON THE RADIO"}, "lead_paragraph": null, "subsection_name": null, "type_of_material": "Article", "document_type": "article", "source": "The New York Times", "multimedia": [], "web_url": "http://query.nytimes.com/gst/abstract.html?res=9D0CE3DB1530E43ABC4953DFB266838B659EDE"}