{"slideshow_credits": null, "_id": "4fc2101f45c1498b0d5d2a6a", "byline": null, "abstract": "illus of Brit SS Queen of Bermuda, Rio de Janeiro", "news_desk": null, "blog": [], "section_name": null, "snippet": "illus of Brit SS Queen of Bermuda, Rio de Janeiro...", "pub_date": "1940-03-01T00:00:00Z", "print_page": "3", "keywords": [{"name": "subject", "value": "EUROPEAN WAR"}, {"name": "subject", "value": "MILITARY ACTION"}, {"name": "subject", "value": "NAVAL"}], "word_count": 39, "headline": {"main": "FORMER BERMUDA LINER NOW IN THE BRITISH NAVY"}, "lead_paragraph": null, "subsection_name": null, "type_of_material": "Article", "document_type": "article", "source": "The New York Times", "multimedia": [], "web_url": "http://query.nytimes.com/gst/abstract.html?res=9C06E0D81F3EE23ABC4953DFB566838B659EDE"}