{"slideshow_credits": null, "_id": "4fc228a245c1498b0d63f26d", "byline": null, "abstract": null, "news_desk": null, "blog": [], "section_name": null, "snippet": null, "pub_date": "1940-02-01T00:00:00Z", "print_page": "11", "keywords": [], "word_count": 106, "headline": {"kicker": "1", "main": "War Relief Funds Get $1,756,608 in 4 Months"}, "lead_paragraph": null, "subsection_name": null, "type_of_material": "Article", "document_type": "article", "source": "The New York Times", "multimedia": [], "web_url": "http://query.nytimes.com/gst/abstract.html?res=9C02EED71331E43ABC4953DFB466838B659EDE"}